{
  "parameters": {
    "voltage_thrs": 15,
    "bin_width": "0.2"
  },
  "results": [
    {
      "PatientID": "100",
      "Entropy": 1.2522941022939948,
      "LASE": 1.9455879422176661
    },
    {
      "PatientID": "101",
      "Entropy": 0.24018273263226786,
      "LASE": 1.2225460751539334
    },
    {
      "PatientID": "102",
      "Entropy": 0.55583358323673182,
      "LASE": 1.0727015009186911
    },
    {
      "PatientID": "103",
      "Entropy": 1.3256498229856628,
      "LASE": 1.7709482022039331
    },
    {
      "PatientID": "104",
      "Entropy": 1.6426227294911719,
      "LASE": 1.9095650474455781
    },
    {
      "PatientID": "105",
      "Entropy": 1.746206004369782,
      "LASE": 2.19979737471915
    },
    {
      "PatientID": "106",
      "Entropy": 0.39302977879774414,
      "LASE": 0.8650043536831411
    },
    {
      "PatientID": "107",
      "Entropy": 1.0400388673360961,
      "LASE": 1.4536641669309984
    },
    {
      "PatientID": "110",
      "Entropy": 1.3761693818629561,
      "LASE": 2.1178113951639554
    },
    {
      "PatientID": "111",
      "Entropy": 1.6236560603248769,
      "LASE": 2.141550409423326
    },
    {
      "PatientID": "112",
      "Entropy": 1.7209731927003611,
      "LASE": 2.1961422049975816
    },
    {
      "PatientID": "113",
      "Entropy": 1.258814285636259,
      "LASE": 1.9159141633282937
    },
    {
      "PatientID": "115",
      "Entropy": 0.59014715538132356,
      "LASE": 1.0046155451599954
    },
    {
      "PatientID": "117",
      "Entropy": 0.2046495120576477,
      "LASE": 0.82645379381555784
    },
    {
      "PatientID": "118",
      "Entropy": 0,
      "LASE": 0
    },
    {
      "PatientID": "119_1",
      "Entropy": -0.427988024996413,
      "LASE": 0.56816205158209709
    },
    {
      "PatientID": "119_2",
      "Entropy": 0.59014715538132356,
      "LASE": 1.0046155451599954
    },
    {
      "PatientID": "120",
      "Entropy": -0.02924099319766027,
      "LASE": 0.68064672033408358
    },
    {
      "PatientID": "123",
      "Entropy": 0.18728758740785523,
      "LASE": 1.0916078956703943
    },
    {
      "PatientID": "124",
      "Entropy": 0.71528134803303467,
      "LASE": 1.354802240169106
    },
    {
      "PatientID": "125",
      "Entropy": 1.4783053326425535,
      "LASE": 1.9835581114161533
    },
    {
      "PatientID": "126",
      "Entropy": 0.9675557671795485,
      "LASE": 1.6104921078218803
    },
    {
      "PatientID": "127",
      "Entropy": 0.565389618256747,
      "LASE": 1.0615406477189502
    },
    {
      "PatientID": "128",
      "Entropy": 0.17419570257493966,
      "LASE": 0.75531636286437753
    },
    {
      "PatientID": "129",
      "Entropy": 0.73368323660579571,
      "LASE": 1.3178347929585381
    },
    {
      "PatientID": "131",
      "Entropy": 0.0783554633250092,
      "LASE": 0.82343793570028789
    },
    {
      "PatientID": "134",
      "Entropy": 1.6739509180284748,
      "LASE": 2.2037748451910817
    },
    {
      "PatientID": "135",
      "Entropy": 0.24412963905146445,
      "LASE": 1.0208643811028988
    },
    {
      "PatientID": "137",
      "Entropy": 1.4004614450441639,
      "LASE": 2.0724910789967019
    },
    {
      "PatientID": "138",
      "Entropy": 0.24412963905146445,
      "LASE": 1.0208643811028988
    },
    {
      "PatientID": "139",
      "Entropy": 1.1793636071698288,
      "LASE": 1.6861239580087382
    },
    {
      "PatientID": "140",
      "Entropy": 1.4538691666194341,
      "LASE": 2.1692523990616932
    },
    {
      "PatientID": "142",
      "Entropy": 1.5489458758794894,
      "LASE": 2.0039251353130485
    },
    {
      "PatientID": "143",
      "Entropy": -0.02253222728507831,
      "LASE": 0.7772972716078923
    },
    {
      "PatientID": "144",
      "Entropy": 1.0068801910047676,
      "LASE": 1.8445423791127331
    },
    {
      "PatientID": "145",
      "Entropy": 0.9870426358649278,
      "LASE": 1.4427138287349501
    },
    {
      "PatientID": "146",
      "Entropy": 0.4147182766624653,
      "LASE": 0.91108932206496207
    },
    {
      "PatientID": "147",
      "Entropy": 1.2277252776109269,
      "LASE": 1.718719049680052
    },
    {
      "PatientID": "148",
      "Entropy": 0.80376661183716824,
      "LASE": 1.4341402401670862
    },
    {
      "PatientID": "149",
      "Entropy": 0.24412963905146445,
      "LASE": 1.0208643811028988
    },
    {
      "PatientID": "150",
      "Entropy": 1.7464786900261349,
      "LASE": 2.0809106285058423
    },
    {
      "PatientID": "151",
      "Entropy": 1.4402359242076541,
      "LASE": 2.0041665070036414
    },
    {
      "PatientID": "40",
      "Entropy": 0.6198661783259436,
      "LASE": 1.6974428447097629
    },
    {
      "PatientID": "41",
      "Entropy": 1.5193781409470863,
      "LASE": 1.9276384542728613
    },
    {
      "PatientID": "42",
      "Entropy": 0.33118819153186552,
      "LASE": 1.191870928720437
    },
    {
      "PatientID": "43",
      "Entropy": 0.64573427237461023,
      "LASE": 1.1963217457424358
    },
    {
      "PatientID": "45",
      "Entropy": 0.87346708111877525,
      "LASE": 1.4300933801297908
    },
    {
      "PatientID": "46",
      "Entropy": 0.6864378690322035,
      "LASE": 1.8609583790606823
    },
    {
      "PatientID": "47",
      "Entropy": 0.77198710789473668,
      "LASE": 1.3004462524369831
    },
    {
      "PatientID": "48",
      "Entropy": 0.68986414321851774,
      "LASE": 1.2928875603785592
    },
    {
      "PatientID": "49",
      "Entropy": 1.0574646892170161,
      "LASE": 1.6247020046939211
    },
    {
      "PatientID": "50",
      "Entropy": 0.66131726409838065,
      "LASE": 1.4328993182156797
    },
    {
      "PatientID": "51",
      "Entropy": 0.89165181477483579,
      "LASE": 1.44247362894137
    },
    {
      "PatientID": "52",
      "Entropy": 0.673341119902007,
      "LASE": 1.2836342829437297
    },
    {
      "PatientID": "53",
      "Entropy": 0.934660379984771,
      "LASE": 1.4345861859359441
    },
    {
      "PatientID": "55",
      "Entropy": 0.58002476970108874,
      "LASE": 1.2332431082326407
    },
    {
      "PatientID": "56",
      "Entropy": 1.746206004369782,
      "LASE": 2.2058180771669127
    },
    {
      "PatientID": "57",
      "Entropy": 1.746206004369782,
      "LASE": 2.19979737471915
    },
    {
      "PatientID": "58",
      "Entropy": 0.24412963905146445,
      "LASE": 1.0208643811028988
    },
    {
      "PatientID": "59",
      "Entropy": 0.24412963905146445,
      "LASE": 1.0208643811028988
    },
    {
      "PatientID": "60",
      "Entropy": 0.24412963905146445,
      "LASE": 1.0208643811028988
    },
    {
      "PatientID": "61",
      "Entropy": 1.6965201629733391,
      "LASE": 1.8777786323423185
    },
    {
      "PatientID": "62",
      "Entropy": 0.47595863842978114,
      "LASE": 1.1854616795706849
    },
    {
      "PatientID": "63",
      "Entropy": 1.4844485464329102,
      "LASE": 1.8680393190766142
    },
    {
      "PatientID": "64",
      "Entropy": 1.346105435373824,
      "LASE": 1.9308147894842287
    },
    {
      "PatientID": "65",
      "Entropy": 1.3901536257061269,
      "LASE": 1.9194492302754254
    },
    {
      "PatientID": "66",
      "Entropy": 0.63081354250407373,
      "LASE": 1.2075895104077408
    },
    {
      "PatientID": "68",
      "Entropy": 0.96448456827761153,
      "LASE": 1.717314718517027
    },
    {
      "PatientID": "70",
      "Entropy": 0.700245560412285,
      "LASE": 1.4238497970135515
    },
    {
      "PatientID": "71",
      "Entropy": 1.2204369729385223,
      "LASE": 1.9124676428845115
    },
    {
      "PatientID": "72",
      "Entropy": 0.902090031521223,
      "LASE": 1.2818123739125082
    },
    {
      "PatientID": "73",
      "Entropy": 1.0052069241259669,
      "LASE": 1.8464235943026426
    },
    {
      "PatientID": "74",
      "Entropy": 1.2960843539210052,
      "LASE": 1.7507409905097988
    },
    {
      "PatientID": "75",
      "Entropy": 0.56597013379628636,
      "LASE": 1.4336065668165923
    },
    {
      "PatientID": "76",
      "Entropy": 0.043429661967895772,
      "LASE": 0.78034866504643774
    },
    {
      "PatientID": "77",
      "Entropy": 0.77092242588860116,
      "LASE": 1.3286421684675498
    },
    {
      "PatientID": "78",
      "Entropy": 0.75260129460525449,
      "LASE": 1.2568013908291367
    },
    {
      "PatientID": "79",
      "Entropy": 1.0658192636060513,
      "LASE": 1.6850364149904931
    },
    {
      "PatientID": "80",
      "Entropy": 1.972808291894631,
      "LASE": 2.2832616639968437
    },
    {
      "PatientID": "81",
      "Entropy": 0.88597361134399866,
      "LASE": 1.5421997395153533
    },
    {
      "PatientID": "82",
      "Entropy": 0.281258271412268,
      "LASE": 1.4736684693835824
    },
    {
      "PatientID": "83",
      "Entropy": 1.3808565885345188,
      "LASE": 1.9382779047830543
    },
    {
      "PatientID": "84",
      "Entropy": 1.5383039516537778,
      "LASE": 1.9994977732263262
    },
    {
      "PatientID": "85",
      "Entropy": 1.7443195857960692,
      "LASE": 2.1642985081109964
    },
    {
      "PatientID": "86",
      "Entropy": 1.0521418963761449,
      "LASE": 1.5041286936653229
    },
    {
      "PatientID": "87",
      "Entropy": 1.2044293276180678,
      "LASE": 1.7743080599619694
    },
    {
      "PatientID": "88",
      "Entropy": 0.39738117303948051,
      "LASE": 1.228897551888936
    },
    {
      "PatientID": "89",
      "Entropy": 1.6624119615653774,
      "LASE": 1.88154451542788
    },
    {
      "PatientID": "90",
      "Entropy": 1.076528571047829,
      "LASE": 1.6135450476724424
    },
    {
      "PatientID": "91",
      "Entropy": 0.7558031065685078,
      "LASE": 1.4146297367237273
    },
    {
      "PatientID": "92",
      "Entropy": 1.2623779118599325,
      "LASE": 1.9345341120189314
    },
    {
      "PatientID": "93",
      "Entropy": 1.4246973893347044,
      "LASE": 1.7969620860677356
    },
    {
      "PatientID": "94",
      "Entropy": 1.3407171603177377,
      "LASE": 1.9198551705579405
    },
    {
      "PatientID": "95",
      "Entropy": 0.79381999245833756,
      "LASE": 1.3042376385834549
    },
    {
      "PatientID": "96",
      "Entropy": 1.3341866823345094,
      "LASE": 1.8916983940727994
    },
    {
      "PatientID": "97",
      "Entropy": 0.738032542592159,
      "LASE": 1.6362339919858571
    },
    {
      "PatientID": "98",
      "Entropy": 0.25781858493906995,
      "LASE": 0.97085501566115506
    }
  ]
}